<annotation>
	<folder>totest</folder>
	<filename>271591667_1733558000318156_5246672707260840911_n.jpg</filename>
	<path>C:\Users\cyrin\OneDrive\Bureau\AugmentLabelIMG-master\totest\271591667_1733558000318156_5246672707260840911_n.jpg</path>
	<source>
		<database>Unknown</database>
	</source>
	<size>
		<width>736</width>
		<height>748</height>
		<depth>3</depth>
	</size>
	<segmented>0</segmented>
	<object>
		<name>UNO R3</name>
		<pose>Unspecified</pose>
		<truncated>0</truncated>
		<difficult>0</difficult>
		<bndbox>
			<xmin>53</xmin>
			<ymin>299</ymin>
			<xmax>655</xmax>
			<ymax>724</ymax>
		</bndbox>
	</object>
</annotation>
