<annotation>
	<filename>265629773_315428466971110_7200529079512009288_n-270-mirrored.jpg</filename>
	<source>
		<database>Unknown</database>
	</source>
	<size>
		<width>720</width>
		<height>960</height>
		<depth>3</depth>
	</size>
	<segmented>0</segmented>
	<object>
		<name>UNO R3</name>
		<pose>Unspecified</pose>
		<truncated>0</truncated>
		<difficult>0</difficult>
		<bndbox>
			<xmin>326</xmin>
			<ymin>215</ymin>
			<xmax>494</xmax>
			<ymax>490</ymax>
		</bndbox>
	</object>
	<object>
		<name>BATTERY BOX</name>
		<pose>Unspecified</pose>
		<truncated>0</truncated>
		<difficult>0</difficult>
		<bndbox>
			<xmin>733</xmin>
			<ymin>349</ymin>
			<xmax>780</xmax>
			<ymax>437</ymax>
		</bndbox>
	</object>
</annotation>
