<annotation>
	<filename>264960374_307246794623557_6006383942063004777_n-270-mirrored.jpg</filename>
	<source>
		<database>Unknown</database>
	</source>
	<size>
		<width>720</width>
		<height>960</height>
		<depth>3</depth>
	</size>
	<segmented>0</segmented>
	<object>
		<name>SENSOR</name>
		<pose>Unspecified</pose>
		<truncated>0</truncated>
		<difficult>0</difficult>
		<bndbox>
			<xmin>737</xmin>
			<ymin>281</ymin>
			<xmax>795</xmax>
			<ymax>349</ymax>
		</bndbox>
	</object>
	<object>
		<name>MOTOR</name>
		<pose>Unspecified</pose>
		<truncated>0</truncated>
		<difficult>0</difficult>
		<bndbox>
			<xmin>588</xmin>
			<ymin>285</ymin>
			<xmax>657</xmax>
			<ymax>352</ymax>
		</bndbox>
	</object>
	<object>
		<name>UNO R3</name>
		<pose>Unspecified</pose>
		<truncated>0</truncated>
		<difficult>0</difficult>
		<bndbox>
			<xmin>704</xmin>
			<ymin>488</ymin>
			<xmax>778</xmax>
			<ymax>550</ymax>
		</bndbox>
	</object>
	<object>
		<name>5V EXPANSION</name>
		<pose>Unspecified</pose>
		<truncated>0</truncated>
		<difficult>0</difficult>
		<bndbox>
			<xmin>765</xmin>
			<ymin>391</ymin>
			<xmax>843</xmax>
			<ymax>462</ymax>
		</bndbox>
	</object>
	<object>
		<name>SENSOR</name>
		<pose>Unspecified</pose>
		<truncated>0</truncated>
		<difficult>0</difficult>
		<bndbox>
			<xmin>671</xmin>
			<ymin>342</ymin>
			<xmax>705</xmax>
			<ymax>364</ymax>
		</bndbox>
	</object>
	<object>
		<name>MOTOR</name>
		<pose>Unspecified</pose>
		<truncated>0</truncated>
		<difficult>0</difficult>
		<bndbox>
			<xmin>238</xmin>
			<ymin>357</ymin>
			<xmax>364</xmax>
			<ymax>487</ymax>
		</bndbox>
	</object>
	<object>
		<name>BATTERY BOX</name>
		<pose>Unspecified</pose>
		<truncated>0</truncated>
		<difficult>0</difficult>
		<bndbox>
			<xmin>587</xmin>
			<ymin>482</ymin>
			<xmax>626</xmax>
			<ymax>531</ymax>
		</bndbox>
	</object>
</annotation>
