<annotation>
	<filename>265428390_339428870898933_2205098220290409677_n-180-mirrored.jpg</filename>
	<source>
		<database>Unknown</database>
	</source>
	<size>
		<width>720</width>
		<height>960</height>
		<depth>3</depth>
	</size>
	<segmented>0</segmented>
	<object>
		<name>SENSOR</name>
		<pose>Unspecified</pose>
		<truncated>0</truncated>
		<difficult>0</difficult>
		<bndbox>
			<xmin>403</xmin>
			<ymin>385</ymin>
			<xmax>470</xmax>
			<ymax>420</ymax>
		</bndbox>
	</object>
	<object>
		<name>MOTOR</name>
		<pose>Unspecified</pose>
		<truncated>0</truncated>
		<difficult>0</difficult>
		<bndbox>
			<xmin>316</xmin>
			<ymin>392</ymin>
			<xmax>401</xmax>
			<ymax>482</ymax>
		</bndbox>
	</object>
	<object>
		<name>5V EXPANSION</name>
		<pose>Unspecified</pose>
		<truncated>0</truncated>
		<difficult>0</difficult>
		<bndbox>
			<xmin>342</xmin>
			<ymin>466</ymin>
			<xmax>416</xmax>
			<ymax>536</ymax>
		</bndbox>
	</object>
	<object>
		<name>BATTERY BOX</name>
		<pose>Unspecified</pose>
		<truncated>0</truncated>
		<difficult>0</difficult>
		<bndbox>
			<xmin>147</xmin>
			<ymin>693</ymin>
			<xmax>233</xmax>
			<ymax>748</ymax>
		</bndbox>
	</object>
</annotation>
