<annotation>
	<filename>265757101_649785689533335_7809391791092803981_n-270.jpg</filename>
	<source>
		<database>Unknown</database>
	</source>
	<size>
		<width>720</width>
		<height>960</height>
		<depth>3</depth>
	</size>
	<segmented>0</segmented>
	<object>
		<name>SENSOR</name>
		<pose>Unspecified</pose>
		<truncated>0</truncated>
		<difficult>0</difficult>
		<bndbox>
			<xmin>453</xmin>
			<ymin>321</ymin>
			<xmax>489</xmax>
			<ymax>390</ymax>
		</bndbox>
	</object>
	<object>
		<name>5V EXPANSION</name>
		<pose>Unspecified</pose>
		<truncated>0</truncated>
		<difficult>0</difficult>
		<bndbox>
			<xmin>502</xmin>
			<ymin>261</ymin>
			<xmax>615</xmax>
			<ymax>388</ymax>
		</bndbox>
	</object>
	<object>
		<name>BATTERY BOX</name>
		<pose>Unspecified</pose>
		<truncated>0</truncated>
		<difficult>0</difficult>
		<bndbox>
			<xmin>300</xmin>
			<ymin>561</ymin>
			<xmax>356</xmax>
			<ymax>667</ymax>
		</bndbox>
	</object>
</annotation>
