<annotation>
	<filename>270058268_443593457434042_8131052346811771991_n-270-mirrored.jpg</filename>
	<source>
		<database>Unknown</database>
	</source>
	<size>
		<width>720</width>
		<height>960</height>
		<depth>3</depth>
	</size>
	<segmented>0</segmented>
	<object>
		<name>BATTERY BOX</name>
		<pose>Unspecified</pose>
		<truncated>1</truncated>
		<difficult>0</difficult>
		<bndbox>
			<xmin>98</xmin>
			<ymin>0</ymin>
			<xmax>625</xmax>
			<ymax>185</ymax>
		</bndbox>
	</object>
	<object>
		<name>MOTOR</name>
		<pose>Unspecified</pose>
		<truncated>0</truncated>
		<difficult>0</difficult>
		<bndbox>
			<xmin>158</xmin>
			<ymin>320</ymin>
			<xmax>495</xmax>
			<ymax>668</ymax>
		</bndbox>
	</object>
	<object>
		<name>SENSOR</name>
		<pose>Unspecified</pose>
		<truncated>0</truncated>
		<difficult>0</difficult>
		<bndbox>
			<xmin>501</xmin>
			<ymin>448</ymin>
			<xmax>722</xmax>
			<ymax>695</ymax>
		</bndbox>
	</object>
</annotation>
